pyrallelism/__init__.py
pyrallelism/evaluator.py
pyrallelism/pyrallelism.py
pyrallelism/primitives/__init__.py
pyrallelism/primitives/evaluation_metric.py
pyrallelism/primitives/typing.py
pyrallelism/primitives/assignment/__init__.py
pyrallelism/primitives/assignment/lsa.py
pyrallelism/primitives/conversion/__init__.py
pyrallelism/primitives/conversion/base.py
pyrallelism/primitives/conversion/instantiations.py
pyrallelism/primitives/loading/__init__.py
pyrallelism/primitives/loading/base.py
pyrallelism/primitives/loading/instantiations.py
pyrallelism/primitives/loading/interface.py
pyrallelism/primitives/score/__init__.py
pyrallelism/primitives/score/base.py
pyrallelism/primitives/score/instantiations.py
pyrallelism/primitives/size/__init__.py
pyrallelism/primitives/size/base.py
pyrallelism/primitives/size/instantiations.py
pyrallelism/structures/__init__.py
pyrallelism/structures/confusion_matrix.py
pyrallelism/utils/__init__.py
pyrallelism/utils/command_line_helpers.py
pyrallelism/utils/help_messages.py
pyrallelism/utils/output_format.py
pyrallelism-1.1.1.dist-info/LICENSE
pyrallelism-1.1.1.dist-info/METADATA
pyrallelism-1.1.1.dist-info/WHEEL
pyrallelism-1.1.1.dist-info/entry_points.txt
pyrallelism-1.1.1.dist-info/top_level.txt
pyrallelism-1.1.1.dist-info/RECORD
