Metadata-Version: 2.1
Name: pyrallelism
Version: 1.1.1
Summary: Interface and Utilities for Bipartite Parallelism Metrics
Home-page: https://github.com/Mythologos/pyrallelism
Author: Stephen Bothwell
Author-email: Stephen Bothwell <sbothwel@nd.edu>
License: MIT License
Project-URL: Repository, https://github.com/Mythologos/pyrallelism
Keywords: Metrics,Evaluation,Rhetorical Parallelism Detection
Classifier: Intended Audience :: Science/Research
Classifier: Intended Audience :: Education
Classifier: License :: OSI Approved :: MIT License
Classifier: Operating System :: OS Independent
Classifier: Programming Language :: Python
Classifier: Programming Language :: Python :: 3.11
Classifier: Topic :: Scientific/Engineering
Classifier: Topic :: Text Processing :: Linguistic
Classifier: Topic :: Text Processing :: Markup :: XML
Classifier: Topic :: Utilities
Requires-Python: >=3.11
License-File: LICENSE
Requires-Dist: natsort >=7.1
Requires-Dist: numpy >=1.25
Requires-Dist: scipy >=1.10
